Metadata-Version: 2.4
Name: iflow-mcp_klavis-ai_youtube
Version: 1.0.0
Summary: YouTube MCP Server - A Model Context Protocol server for YouTube integration
Author-email: Klavis AI <support@klavis.ai>
License: Apache-2.0
Project-URL: Homepage, https://github.com/klavis-ai/klavis
Project-URL: Repository, https://github.com/klavis-ai/klavis
Project-URL: Documentation, https://www.klavis.ai/docs
Classifier: Development Status :: 4 - Beta
Classifier: Intended Audience :: Developers
Classifier: License :: OSI Approved :: Apache Software License
Classifier: Programming Language :: Python :: 3
Classifier: Programming Language :: Python :: 3.8
Classifier: Programming Language :: Python :: 3.9
Classifier: Programming Language :: Python :: 3.10
Classifier: Programming Language :: Python :: 3.11
Classifier: Programming Language :: Python :: 3.12
Requires-Python: >=3.8
Requires-Dist: mcp==1.11.0
Requires-Dist: pydantic
Requires-Dist: fastapi
Requires-Dist: uvicorn[standard]
Requires-Dist: aiohttp
Requires-Dist: python-dotenv
Requires-Dist: typing-extensions
Requires-Dist: youtube-transcript-api>=1.2.3
Requires-Dist: google-api-python-client>=2.100.0
Requires-Dist: google-auth>=2.23.0
Requires-Dist: google-auth-oauthlib>=1.1.0
Requires-Dist: google-auth-httplib2>=0.1.0
Requires-Dist: click
Requires-Dist: starlette
